automatically/__init__.py
automatically/_version.py
automatically/unsafe.py
automatically-0.1.0.dist-info/LICENSE
automatically-0.1.0.dist-info/METADATA
automatically-0.1.0.dist-info/WHEEL
automatically-0.1.0.dist-info/top_level.txt
automatically-0.1.0.dist-info/RECORD
