Metadata-Version: 2.1
Name: automatically
Version: 0.1.0
Summary: Install packages automatically
Author-email: Jonas Loos <automatically@jloos.de>
License: MIT License
Project-URL: Homepage, https://github.com/JonasLoos/automatically
Requires-Python: >=3.9
License-File: LICENSE
